{
  "index": "Getting Started",
  "multiprotocols": "Multi Protocol API Platform",
  "-": {
    "title": "Platform Guide",
    "type": "separator"
  },
  "platform": "API Platform",
  "--": {
    "title": "API Playgrounds",
    "type": "separator"
  },
  "rest": "Rest APIs",
  "graphql": "GraphQL",
  "websocket": "WebSocket",
  "socket-io": "Socket.IO",
  "---": {
    "title": "Firecamp CLI",
    "type": "separator"
  },
  "cli": "Firecamp CLI",
  "about": {
    "title": "About",
    "type": "page"
  },
  "contact": {
    "title": "Twitter ↗",
    "type": "page",
    "href": "https://twitter.com/firecampdev",
    "newWindow": true
  }
}
